{
	"textures": {
		"0": "block/chorus_flower_dead",
		"particle": "block/chorus_plant"
	},
	"elements": [
		{
			"from": [3, 0, 3],
			"to": [13, 3, 13],
			"faces": {
				"north": {"uv": [8.75, 7.25, 11.25, 8], "texture": "#0"},
				"east": {"uv": [8.75, 7.25, 11.25, 8], "texture": "#0"},
				"south": {"uv": [8.75, 7.25, 11.25, 8], "texture": "#0"},
				"west": {"uv": [8.75, 7.25, 11.25, 8], "texture": "#0"}
			}
		},
		{
			"from": [3, 3, 0],
			"to": [13, 13, 16],
			"faces": {
				"east": {"uv": [8, 4.75, 12, 7.25], "texture": "#0"},
				"west": {"uv": [8, 4.75, 12, 7.25], "texture": "#0"},
				"up": {"uv": [12.75, 8, 15.25, 12], "texture": "#0"},
				"down": {"uv": [12.75, 12, 15.25, 16], "texture": "#0"}
			}
		},
		{
			"from": [0, 3, 3],
			"to": [16, 13, 13],
			"faces": {
				"north": {"uv": [8, 4.75, 12, 7.25], "texture": "#0"},
				"south": {"uv": [8, 4.75, 12, 7.25], "texture": "#0"},
				"up": {"uv": [12, 8.75, 16, 11.25], "texture": "#0"},
				"down": {"uv": [12, 12.75, 16, 15.25], "texture": "#0"}
			}
		}
	]
}