{
	"parent": "block/block",
	"texture_size": [16, 32],
	"textures": {
		"0": "block/entity/end_crystal"
	},
	"elements": [
		{
			"from": [3, 3, 3],
			"to": [13, 13, 13],
			"faces": {
				"north": {"uv": [0, 8, 16, 16], "texture": "#0"},
				"east": {"uv": [0, 8, 16, 16], "texture": "#0"},
				"south": {"uv": [0, 8, 16, 16], "texture": "#0"},
				"west": {"uv": [0, 8, 16, 16], "texture": "#0"},
				"up": {"uv": [0, 8, 16, 16], "texture": "#0"},
				"down": {"uv": [0, 8, 16, 16], "texture": "#0"}
			}
		},
		{
			"from": [3, 3, 13],
			"to": [13, 13, 3],
			"faces": {
				"north": {"uv": [0, 8, 16, 16], "texture": "#0"},
				"east": {"uv": [0, 8, 16, 16], "texture": "#0"},
				"south": {"uv": [0, 8, 16, 16], "texture": "#0"},
				"west": {"uv": [0, 8, 16, 16], "texture": "#0"},
				"up": {"uv": [0, 8, 16, 16], "texture": "#0"},
				"down": {"uv": [0, 8, 16, 16], "texture": "#0"}
			}
		},
		{
			"from": [1, 1, 1],
			"to": [15, 15, 15],
			"rotation": {"angle": -45, "axis": "x", "origin": [8, 8, 8]},
			"faces": {
				"north": {"uv": [0, 0, 16, 8], "texture": "#0"},
				"east": {"uv": [0, 0, 16, 8], "texture": "#0"},
				"south": {"uv": [0, 0, 16, 8], "texture": "#0"},
				"west": {"uv": [0, 0, 16, 8], "texture": "#0"},
				"up": {"uv": [0, 0, 16, 8], "texture": "#0"},
				"down": {"uv": [0, 0, 16, 8], "texture": "#0"}
			}
		},
		{
			"from": [15, 1, 1],
			"to": [1, 15, 15],
			"rotation": {"angle": -45, "axis": "x", "origin": [8, 8, 8]},
			"faces": {
				"north": {"uv": [0, 0, 16, 8], "texture": "#0"},
				"east": {"uv": [0, 0, 16, 8], "texture": "#0"},
				"south": {"uv": [0, 0, 16, 8], "texture": "#0"},
				"west": {"uv": [0, 0, 16, 8], "texture": "#0"},
				"up": {"uv": [0, 0, 16, 8], "texture": "#0"},
				"down": {"uv": [0, 0, 16, 8], "texture": "#0"}
			}
		},
		{
			"from": [2, 2, 2],
			"to": [14, 14, 14],
			"rotation": {"angle": 45, "axis": "z", "origin": [8, 8, 8]},
			"faces": {
				"north": {"uv": [0, 0, 16, 8], "texture": "#0"},
				"east": {"uv": [0, 0, 16, 8], "texture": "#0"},
				"south": {"uv": [0, 0, 16, 8], "texture": "#0"},
				"west": {"uv": [0, 0, 16, 8], "texture": "#0"},
				"up": {"uv": [0, 0, 16, 8], "texture": "#0"},
				"down": {"uv": [0, 0, 16, 8], "texture": "#0"}
			}
		},
		{
			"from": [2, 2, 14],
			"to": [14, 14, 2],
			"rotation": {"angle": 45, "axis": "z", "origin": [8, 8, 8]},
			"faces": {
				"north": {"uv": [0, 0, 16, 8], "texture": "#0"},
				"east": {"uv": [0, 0, 16, 8], "texture": "#0"},
				"south": {"uv": [0, 0, 16, 8], "texture": "#0"},
				"west": {"uv": [0, 0, 16, 8], "texture": "#0"},
				"up": {"uv": [0, 0, 16, 8], "texture": "#0"},
				"down": {"uv": [0, 0, 16, 8], "texture": "#0"}
			}
		}
	]
}